[{"unitNotes": null, "courseDescription": null, "subjectNotes": null, "coreCodes": [], "courseNotes": null, "title": "IND STY CELL BIO/NEU", "supplementCode": "  ", "subjectGroupNotes": null, "courseNumber": "201", "campusCode": "NB", "synopsisUrl": "http://biology.rutgers.edu/biological-sciences/courses#cbn", "preReqNotes": null, "openSections": 1, "credits": null, "offeringUnitCode": "01", "expandedTitle": null, "offeringUnitTitle": null, "sections": [{"minors": [], "sessionDates": null, "honorPrograms": [], "number": "01", "unitMajors": [], "subtitle": null, "specialPermissionDropCodeDescription": null, "specialPermissionAddCodeDescription": "Department staff", "subtopic": null, "majors": [], "index": "29194", "sectionNotes": null, "specialPermissionDropCode": null, "comments": [], "crossListedSections": [], "legendKey": null, "meetingTimes": [{"campusName": null, "startTime": null, "meetingDay": null, "meetingModeDesc": "RSCH-MA", "roomNumber": null, "campusLocation": null, "buildingCode": null, "pmCode": null, "baClassHours": "B", "campusAbbrev": null, "endTime": null, "meetingModeCode": "23"}], "specialPermissionAddCode": "03", "instructors": [], "printed": "Y", "examCode": "A", "campusCode": "NB", "stopPoint": 25, "sectionEligibility": null, "sessionDatePrintIndicator": "Y", "openStatus": true}], "subject": "146"}, {"unitNotes": null, "courseDescription": null, "subjectNotes": null, "coreCodes": [], "courseNotes": null, "title": "IND STY CELL BIO/NEU", "supplementCode": "  ", "subjectGroupNotes": null, "courseNumber": "202", "campusCode": "NB", "synopsisUrl": "http://biology.rutgers.edu/biological-sciences/courses#cbn", "preReqNotes": null, "openSections": 1, "credits": null, "offeringUnitCode": "01", "expandedTitle": null, "offeringUnitTitle": null, "sections": [{"minors": [], "sessionDates": null, "honorPrograms": [], "number": "01", "unitMajors": [], "subtitle": null, "specialPermissionDropCodeDescription": null, "specialPermissionAddCodeDescription": "Department staff", "subtopic": null, "majors": [], "index": "29195", "sectionNotes": null, "specialPermissionDropCode": null, "comments": [], "crossListedSections": [], "legendKey": null, "meetingTimes": [{"campusName": null, "startTime": null, "meetingDay": null, "meetingModeDesc": "RSCH-MA", "roomNumber": null, "campusLocation": null, "buildingCode": null, "pmCode": null, "baClassHours": "B", "campusAbbrev": null, "endTime": null, "meetingModeCode": "23"}], "specialPermissionAddCode": "03", "instructors": [], "printed": "N", "examCode": "A", "campusCode": "NB", "stopPoint": 25, "sectionEligibility": null, "sessionDatePrintIndicator": "Y", "openStatus": true}], "subject": "146"}, {"unitNotes": null, "courseDescription": null, "subjectNotes": null, "coreCodes": [], "courseNotes": null, "title": "FUND OF NEUROBIOLOGY", "supplementCode": "  ", "subjectGroupNotes": null, "courseNumber": "245", "campusCode": "NB", "synopsisUrl": "http://biology.rutgers.edu/biological-sciences/courses#cbn", "preReqNotes": "(01:119:102  and 01:119:102  and 01:119:102  and 01:119:102 ) <em> OR </em> (01:119:116  and 01:119:116  and 01:119:116  and 01:119:116 ) <em> OR </em> (50:120:101  and 50:120:102  and 50:120:102  and 50:120:102 ) <em> OR </em> (62:120:101 GENERAL BIO DISCUSSN and 62:120:102 GENERAL BIO DISCUSSN and 62:120:102 GENERAL BIO DISCUSSN and 62:120:102 GENERAL BIO DISCUSSN) <em> OR </em> (21:120:201  and 21:120:205  and 21:120:205  and 21:120:205 )", "openSections": 0, "credits": 3, "offeringUnitCode": "01", "expandedTitle": null, "offeringUnitTitle": null, "sections": [{"minors": [], "sessionDates": null, "honorPrograms": [], "number": "01", "unitMajors": [], "subtitle": null, "specialPermissionDropCodeDescription": null, "specialPermissionAddCodeDescription": null, "subtopic": null, "majors": [], "index": "23414", "sectionNotes": "PREREQ:01:119:101-102/EQUIVALENTFOR CBN MAJORS AND STUDENTSINTENDING TO MAJOR IN CBN.NON-MAJORS REGISTER FOR 146:295", "specialPermissionDropCode": null, "comments": [{"code": "35", "description": "See online schedule for prereqs"}], "crossListedSections": [], "legendKey": null, "meetingTimes": [{"campusName": "BUSCH", "startTime": "0140", "meetingDay": "M", "meetingModeDesc": "LEC", "roomNumber": "111", "campusLocation": "2", "buildingCode": "PH", "pmCode": "P", "baClassHours": null, "campusAbbrev": "BUS", "endTime": "0300", "meetingModeCode": "02"}, {"campusName": "BUSCH", "startTime": "0140", "meetingDay": "W", "meetingModeDesc": "LEC", "roomNumber": "111", "campusLocation": "2", "buildingCode": "PH", "pmCode": "P", "baClassHours": null, "campusAbbrev": "BUS", "endTime": "0300", "meetingModeCode": "02"}], "specialPermissionAddCode": null, "instructors": [{"name": "AUERBACH,S"}], "printed": "Y", "examCode": "C", "campusCode": "NB", "stopPoint": 0, "sectionEligibility": "JUNIORS ONLY ", "sessionDatePrintIndicator": "Y", "openStatus": false}, {"minors": [], "sessionDates": null, "honorPrograms": [], "number": "02", "unitMajors": [], "subtitle": null, "specialPermissionDropCodeDescription": null, "specialPermissionAddCodeDescription": null, "subtopic": null, "majors": [], "index": "24702", "sectionNotes": "FOR CBN MAJORS AND STUDENTSINTENDING TO MAJOR IN CBNNON-MAJORS REGISTER FOR 146:295", "specialPermissionDropCode": null, "comments": [{"code": "35", "description": "See online schedule for prereqs"}], "crossListedSections": [], "legendKey": null, "meetingTimes": [{"campusName": "BUSCH", "startTime": "0140", "meetingDay": "M", "meetingModeDesc": "LEC", "roomNumber": "111", "campusLocation": "2", "buildingCode": "PH", "pmCode": "P", "baClassHours": null, "campusAbbrev": "BUS", "endTime": "0300", "meetingModeCode": "02"}, {"campusName": "BUSCH", "startTime": "0140", "meetingDay": "W", "meetingModeDesc": "LEC", "roomNumber": "111", "campusLocation": "2", "buildingCode": "PH", "pmCode": "P", "baClassHours": null, "campusAbbrev": "BUS", "endTime": "0300", "meetingModeCode": "02"}], "specialPermissionAddCode": null, "instructors": [], "printed": "Y", "examCode": "C", "campusCode": "NB", "stopPoint": 0, "sectionEligibility": "SOPHOMORES ONLY ", "sessionDatePrintIndicator": "Y", "openStatus": false}, {"minors": [], "sessionDates": null, "honorPrograms": [], "number": "03", "unitMajors": [], "subtitle": null, "specialPermissionDropCodeDescription": null, "specialPermissionAddCodeDescription": null, "subtopic": null, "majors": [], "index": "25326", "sectionNotes": "FOR CBN MAJORS AND STUDENTSINTENDING TO MAJOR IN CBNNON-MAJORS REGISTER FOR 146:295", "specialPermissionDropCode": null, "comments": [{"code": "35", "description": "See online schedule for prereqs"}], "crossListedSections": [], "legendKey": null, "meetingTimes": [{"campusName": "BUSCH", "startTime": "0140", "meetingDay": "W", "meetingModeDesc": "LEC", "roomNumber": "111", "campusLocation": "2", "buildingCode": "PH", "pmCode": "P", "baClassHours": null, "campusAbbrev": "BUS", "endTime": "0300", "meetingModeCode": "02"}, {"campusName": "BUSCH", "startTime": "0140", "meetingDay": "M", "meetingModeDesc": "LEC", "roomNumber": "111", "campusLocation": "2", "buildingCode": "PH", "pmCode": "P", "baClassHours": null, "campusAbbrev": "BUS", "endTime": "0300", "meetingModeCode": "02"}], "specialPermissionAddCode": null, "instructors": [], "printed": "Y", "examCode": "C", "campusCode": "NB", "stopPoint": 0, "sectionEligibility": "ALL EXCEPT 1ST YEAR ", "sessionDatePrintIndicator": "Y", "openStatus": false}], "subject": "146"}, {"unitNotes": null, "courseDescription": null, "subjectNotes": null, "coreCodes": [], "courseNotes": null, "title": "FUND CELL & DEV BIO", "supplementCode": "  ", "subjectGroupNotes": null, "courseNumber": "270", "campusCode": "NB", "synopsisUrl": "http://biology.rutgers.edu/biological-sciences/courses#cbn", "preReqNotes": "(01:119:102  and 01:119:102  and 01:119:102  and 01:119:102 ) <em> OR </em> (01:119:116  and 01:119:116  and 01:119:116  and 01:119:116 ) <em> OR </em> (50:120:101  and 50:120:102  and 50:120:102  and 50:120:102 ) <em> OR </em> (62:120:101 GENERAL BIO DISCUSSN and 62:120:102 GENERAL BIO DISCUSSN and 62:120:102 GENERAL BIO DISCUSSN and 62:120:102 GENERAL BIO DISCUSSN) <em> OR </em> (21:120:201  and 21:120:205  and 21:120:205  and 21:120:205 )", "openSections": 0, "credits": 3, "offeringUnitCode": "01", "expandedTitle": null, "offeringUnitTitle": null, "sections": [{"minors": [], "sessionDates": null, "honorPrograms": [], "number": "01", "unitMajors": [], "subtitle": null, "specialPermissionDropCodeDescription": null, "specialPermissionAddCodeDescription": null, "subtopic": null, "majors": [], "index": "24496", "sectionNotes": "PREREQ:01:119:101-102/EQUIVALENTFOR CBN MAJORS OR STUDENTSINTENDING TO MAJOR IN CBNNON-MAJORS REGISTER FOR 146:295", "specialPermissionDropCode": null, "comments": [{"code": "35", "description": "See online schedule for prereqs"}], "crossListedSections": [], "legendKey": null, "meetingTimes": [{"campusName": "BUSCH", "startTime": "1200", "meetingDay": "F", "meetingModeDesc": "LEC", "roomNumber": "115", "campusLocation": "2", "buildingCode": "PH", "pmCode": "P", "baClassHours": null, "campusAbbrev": "BUS", "endTime": "0120", "meetingModeCode": "02"}, {"campusName": "BUSCH", "startTime": "1200", "meetingDay": "W", "meetingModeDesc": "LEC", "roomNumber": "115", "campusLocation": "2", "buildingCode": "PH", "pmCode": "P", "baClassHours": null, "campusAbbrev": "BUS", "endTime": "0120", "meetingModeCode": "02"}], "specialPermissionAddCode": null, "instructors": [{"name": "BABIARZ/"}, {"name": "KILEDJIAN"}], "printed": "Y", "examCode": "C", "campusCode": "NB", "stopPoint": 0, "sectionEligibility": "JUNIORS ONLY ", "sessionDatePrintIndicator": "Y", "openStatus": false}, {"minors": [], "sessionDates": null, "honorPrograms": [], "number": "02", "unitMajors": [], "subtitle": null, "specialPermissionDropCodeDescription": null, "specialPermissionAddCodeDescription": null, "subtopic": null, "majors": [], "index": "25327", "sectionNotes": "FOR CBN MAJORS OR STUDENTSINTENDING TO MAJOR IN CBNNON-MAJORS REGISTER FOR 146:295", "specialPermissionDropCode": null, "comments": [{"code": "35", "description": "See online schedule for prereqs"}], "crossListedSections": [], "legendKey": null, "meetingTimes": [{"campusName": "BUSCH", "startTime": "1200", "meetingDay": "F", "meetingModeDesc": "LEC", "roomNumber": "115", "campusLocation": "2", "buildingCode": "PH", "pmCode": "P", "baClassHours": null, "campusAbbrev": "BUS", "endTime": "0120", "meetingModeCode": "02"}, {"campusName": "BUSCH", "startTime": "1200", "meetingDay": "W", "meetingModeDesc": "LEC", "roomNumber": "115", "campusLocation": "2", "buildingCode": "PH", "pmCode": "P", "baClassHours": null, "campusAbbrev": "BUS", "endTime": "0120", "meetingModeCode": "02"}], "specialPermissionAddCode": null, "instructors": [], "printed": "Y", "examCode": "C", "campusCode": "NB", "stopPoint": 0, "sectionEligibility": "SOPHOMORES ONLY ", "sessionDatePrintIndicator": "Y", "openStatus": false}, {"minors": [], "sessionDates": null, "honorPrograms": [], "number": "03", "unitMajors": [], "subtitle": null, "specialPermissionDropCodeDescription": null, "specialPermissionAddCodeDescription": null, "subtopic": null, "majors": [], "index": "25328", "sectionNotes": "FOR CBN MAJORS OR STUDENTSINTENDING TO MAJOR IN CBNNON-MAJORS REGISTER FOR 146:295", "specialPermissionDropCode": null, "comments": [{"code": "35", "description": "See online schedule for prereqs"}], "crossListedSections": [], "legendKey": null, "meetingTimes": [{"campusName": "BUSCH", "startTime": "1200", "meetingDay": "F", "meetingModeDesc": "LEC", "roomNumber": "115", "campusLocation": "2", "buildingCode": "PH", "pmCode": "P", "baClassHours": null, "campusAbbrev": "BUS", "endTime": "0120", "meetingModeCode": "02"}, {"campusName": "BUSCH", "startTime": "1200", "meetingDay": "W", "meetingModeDesc": "LEC", "roomNumber": "115", "campusLocation": "2", "buildingCode": "PH", "pmCode": "P", "baClassHours": null, "campusAbbrev": "BUS", "endTime": "0120", "meetingModeCode": "02"}], "specialPermissionAddCode": null, "instructors": [], "printed": "Y", "examCode": "C", "campusCode": "NB", "stopPoint": 0, "sectionEligibility": "ALL EXCEPT 1ST YEAR ", "sessionDatePrintIndicator": "Y", "openStatus": false}], "subject": "146"}, {"unitNotes": null, "courseDescription": null, "subjectNotes": null, "coreCodes": [], "courseNotes": null, "title": "ESS CELL BIO&NEUROSC", "supplementCode": "  ", "subjectGroupNotes": null, "courseNumber": "295", "campusCode": "NB", "synopsisUrl": "http://biology.rutgers.edu/biological-sciences/courses#cbn", "preReqNotes": "(01:119:102  and 01:119:102  and 01:119:102  and 01:119:102 ) <em> OR </em> (01:119:116  and 01:119:116  and 01:119:116  and 01:119:116 ) <em> OR </em> (50:120:101  and 50:120:102  and 50:120:102  and 50:120:102 ) <em> OR </em> (62:120:101 GENERAL BIO DISCUSSN and 62:120:102 GENERAL BIO DISCUSSN and 62:120:102 GENERAL BIO DISCUSSN and 62:120:102 GENERAL BIO DISCUSSN) <em> OR </em> (21:120:201  and 21:120:205  and 21:120:205  and 21:120:205 )", "openSections": 0, "credits": 3, "offeringUnitCode": "01", "expandedTitle": null, "offeringUnitTitle": null, "sections": [{"minors": [], "sessionDates": null, "honorPrograms": [], "number": "01", "unitMajors": [], "subtitle": null, "specialPermissionDropCodeDescription": null, "specialPermissionAddCodeDescription": null, "subtopic": null, "majors": [], "index": "31618", "sectionNotes": "PREREQ: 01:119:101&102 OR EQUIV.NOT FOR CBN MAJORS", "specialPermissionDropCode": null, "comments": [], "crossListedSections": [], "legendKey": null, "meetingTimes": [{"campusName": "BUSCH", "startTime": "1020", "meetingDay": "T", "meetingModeDesc": "LEC", "roomNumber": "115", "campusLocation": "2", "buildingCode": "PH", "pmCode": "A", "baClassHours": null, "campusAbbrev": "BUS", "endTime": "1140", "meetingModeCode": "02"}, {"campusName": "BUSCH", "startTime": "1020", "meetingDay": "F", "meetingModeDesc": "LEC", "roomNumber": "115", "campusLocation": "2", "buildingCode": "PH", "pmCode": "A", "baClassHours": null, "campusAbbrev": "BUS", "endTime": "1140", "meetingModeCode": "02"}], "specialPermissionAddCode": null, "instructors": [{"name": "SCHJOTT, J."}], "printed": "Y", "examCode": "C", "campusCode": "NB", "stopPoint": 0, "sectionEligibility": null, "sessionDatePrintIndicator": "Y", "openStatus": false}], "subject": "146"}, {"unitNotes": null, "courseDescription": null, "subjectNotes": null, "coreCodes": [], "courseNotes": null, "title": "RES CELL BIO&NEUROS", "supplementCode": "  ", "subjectGroupNotes": null, "courseNumber": "307", "campusCode": "NB", "synopsisUrl": "http://biology.rutgers.edu/biological-sciences/courses#cbn", "preReqNotes": null, "openSections": 0, "credits": null, "offeringUnitCode": "01", "expandedTitle": null, "offeringUnitTitle": null, "sections": [{"minors": [], "sessionDates": null, "honorPrograms": [], "number": "01", "unitMajors": [], "subtitle": null, "specialPermissionDropCodeDescription": null, "specialPermissionAddCodeDescription": "Department staff", "subtopic": null, "majors": [], "index": "29189", "sectionNotes": null, "specialPermissionDropCode": null, "comments": [], "crossListedSections": [], "legendKey": null, "meetingTimes": [{"campusName": null, "startTime": null, "meetingDay": null, "meetingModeDesc": "RSCH-MA", "roomNumber": null, "campusLocation": null, "buildingCode": null, "pmCode": null, "baClassHours": "B", "campusAbbrev": null, "endTime": null, "meetingModeCode": "23"}], "specialPermissionAddCode": "03", "instructors": [], "printed": "Y", "examCode": "A", "campusCode": "NB", "stopPoint": 25, "sectionEligibility": null, "sessionDatePrintIndicator": "Y", "openStatus": false}, {"minors": [], "sessionDates": null, "honorPrograms": [], "number": "T1", "unitMajors": [], "subtitle": null, "specialPermissionDropCodeDescription": null, "specialPermissionAddCodeDescription": "Department staff", "subtopic": null, "majors": [], "index": "29230", "sectionNotes": null, "specialPermissionDropCode": null, "comments": [], "crossListedSections": [], "legendKey": null, "meetingTimes": [{"campusName": null, "startTime": null, "meetingDay": null, "meetingModeDesc": "LEC", "roomNumber": null, "campusLocation": null, "buildingCode": null, "pmCode": null, "baClassHours": "B", "campusAbbrev": null, "endTime": null, "meetingModeCode": "02"}], "specialPermissionAddCode": "03", "instructors": [], "printed": "N", "examCode": "A", "campusCode": "NB", "stopPoint": 10, "sectionEligibility": null, "sessionDatePrintIndicator": "Y", "openStatus": false}], "subject": "146"}, {"unitNotes": null, "courseDescription": null, "subjectNotes": null, "coreCodes": [], "courseNotes": null, "title": "RES CELL BIO&NEUROS", "supplementCode": "  ", "subjectGroupNotes": null, "courseNumber": "308", "campusCode": "NB", "synopsisUrl": "http://biology.rutgers.edu/biological-sciences/courses#cbn", "preReqNotes": null, "openSections": 1, "credits": null, "offeringUnitCode": "01", "expandedTitle": null, "offeringUnitTitle": null, "sections": [{"minors": [], "sessionDates": null, "honorPrograms": [], "number": "01", "unitMajors": [], "subtitle": null, "specialPermissionDropCodeDescription": null, "specialPermissionAddCodeDescription": "Department staff", "subtopic": null, "majors": [], "index": "29234", "sectionNotes": null, "specialPermissionDropCode": null, "comments": [], "crossListedSections": [], "legendKey": null, "meetingTimes": [{"campusName": null, "startTime": null, "meetingDay": null, "meetingModeDesc": "RSCH-MA", "roomNumber": null, "campusLocation": null, "buildingCode": null, "pmCode": null, "baClassHours": "B", "campusAbbrev": null, "endTime": null, "meetingModeCode": "23"}], "specialPermissionAddCode": "03", "instructors": [], "printed": "N", "examCode": "A", "campusCode": "NB", "stopPoint": 25, "sectionEligibility": null, "sessionDatePrintIndicator": "Y", "openStatus": true}], "subject": "146"}, {"unitNotes": null, "courseDescription": null, "subjectNotes": null, "coreCodes": [], "courseNotes": null, "title": "HUMAN PARASITOLOGY", "supplementCode": "  ", "subjectGroupNotes": null, "courseNumber": "328", "campusCode": "NB", "synopsisUrl": "http://biology.rutgers.edu/biological-sciences/courses#cbn", "preReqNotes": "(01:119:102  and 01:119:102  and 01:119:102  and 01:119:102 ) <em> OR </em> (01:119:116  and 01:119:116  and 01:119:116  and 01:119:116 ) <em> OR </em> (50:120:101  and 50:120:102  and 50:120:102  and 50:120:102 ) <em> OR </em> (62:120:101 GENERAL BIO DISCUSSN and 62:120:102 GENERAL BIO DISCUSSN and 62:120:102 GENERAL BIO DISCUSSN and 62:120:102 GENERAL BIO DISCUSSN) <em> OR </em> (21:120:201  and 21:120:205  and 21:120:205  and 21:120:205 )", "openSections": 1, "credits": 3, "offeringUnitCode": "01", "expandedTitle": null, "offeringUnitTitle": null, "sections": [{"minors": [], "sessionDates": null, "honorPrograms": [], "number": "01", "unitMajors": [], "subtitle": null, "specialPermissionDropCodeDescription": null, "specialPermissionAddCodeDescription": null, "subtopic": null, "majors": [], "index": "24792", "sectionNotes": "PREREQ: 01:119:101, 01:119:102OR  EQUIVALENT", "specialPermissionDropCode": null, "comments": [{"code": "35", "description": "See online schedule for prereqs"}], "crossListedSections": [], "legendKey": null, "meetingTimes": [{"campusName": "LIVINGSTON", "startTime": "0840", "meetingDay": "W", "meetingModeDesc": "LEC", "roomNumber": "AUD", "campusLocation": "3", "buildingCode": "LSH", "pmCode": "A", "baClassHours": null, "campusAbbrev": "LIV", "endTime": "1140", "meetingModeCode": "02"}], "specialPermissionAddCode": null, "instructors": [{"name": "KEATING, A."}], "printed": "Y", "examCode": "C", "campusCode": "NB", "stopPoint": 0, "sectionEligibility": null, "sessionDatePrintIndicator": "Y", "openStatus": false}, {"minors": [], "sessionDates": null, "honorPrograms": [], "number": "03", "unitMajors": [], "subtitle": null, "specialPermissionDropCodeDescription": null, "specialPermissionAddCodeDescription": "Department staff", "subtopic": null, "majors": [], "index": "24793", "sectionNotes": "ONLY TO UC STUDENTS", "specialPermissionDropCode": null, "comments": [{"code": "35", "description": "See online schedule for prereqs"}], "crossListedSections": [], "legendKey": null, "meetingTimes": [{"campusName": "LIVINGSTON", "startTime": "0840", "meetingDay": "W", "meetingModeDesc": "LEC", "roomNumber": "AUD", "campusLocation": "3", "buildingCode": "LSH", "pmCode": "A", "baClassHours": null, "campusAbbrev": "LIV", "endTime": "1140", "meetingModeCode": "02"}], "specialPermissionAddCode": "03", "instructors": [{"name": "KEATING, A."}], "printed": "Y", "examCode": "C", "campusCode": "NB", "stopPoint": 20, "sectionEligibility": null, "sessionDatePrintIndicator": "Y", "openStatus": true}], "subject": "146"}, {"unitNotes": null, "courseDescription": null, "subjectNotes": null, "coreCodes": [], "courseNotes": null, "title": "HUMAN PARASIT LAB", "supplementCode": "  ", "subjectGroupNotes": null, "courseNumber": "329", "campusCode": "NB", "synopsisUrl": "http://biology.rutgers.edu/biological-sciences/courses#cbn", "preReqNotes": "(01:119:102 )<em> OR </em>(01:119:117 )", "openSections": 1, "credits": 1, "offeringUnitCode": "01", "expandedTitle": "HUMAN PARASITOLOGY LABORATORY                                                   ", "offeringUnitTitle": null, "sections": [{"minors": [], "sessionDates": null, "honorPrograms": [], "number": "01", "unitMajors": [], "subtitle": null, "specialPermissionDropCodeDescription": null, "specialPermissionAddCodeDescription": null, "subtopic": null, "majors": [], "index": "25332", "sectionNotes": "PRE/COREQ: 01:146:328;LABS BEGIN THE WEEK OF SEPT.9TH", "specialPermissionDropCode": null, "comments": [], "crossListedSections": [], "legendKey": null, "meetingTimes": [{"campusName": "BUSCH", "startTime": "0140", "meetingDay": "T", "meetingModeDesc": "LAB", "roomNumber": "B130", "campusLocation": "2", "buildingCode": "NH", "pmCode": "P", "baClassHours": null, "campusAbbrev": "BUS", "endTime": "0440", "meetingModeCode": "05"}], "specialPermissionAddCode": null, "instructors": [{"name": "KEATING, A."}], "printed": "Y", "examCode": "A", "campusCode": "NB", "stopPoint": 0, "sectionEligibility": "JUNIORS AND SENIORS ", "sessionDatePrintIndicator": "Y", "openStatus": false}, {"minors": [], "sessionDates": null, "honorPrograms": [], "number": "02", "unitMajors": [], "subtitle": null, "specialPermissionDropCodeDescription": null, "specialPermissionAddCodeDescription": null, "subtopic": null, "majors": [], "index": "25333", "sectionNotes": "PRE/COREQ: 01:146:328;LABS BEGIN WEEK OF SEPT. 9TH", "specialPermissionDropCode": null, "comments": [], "crossListedSections": [], "legendKey": null, "meetingTimes": [{"campusName": "BUSCH", "startTime": "0640", "meetingDay": "T", "meetingModeDesc": "LAB", "roomNumber": "B130", "campusLocation": "2", "buildingCode": "NH", "pmCode": "P", "baClassHours": null, "campusAbbrev": "BUS", "endTime": "0930", "meetingModeCode": "05"}], "specialPermissionAddCode": null, "instructors": [{"name": "KEATING, A."}], "printed": "Y", "examCode": "A", "campusCode": "NB", "stopPoint": 0, "sectionEligibility": "JUNIORS AND SENIORS ", "sessionDatePrintIndicator": "Y", "openStatus": false}, {"minors": [], "sessionDates": null, "honorPrograms": [], "number": "03", "unitMajors": [], "subtitle": null, "specialPermissionDropCodeDescription": null, "specialPermissionAddCodeDescription": null, "subtopic": null, "majors": [], "index": "31534", "sectionNotes": "PRE/COREQ: 01:146:328;LABS BEGIN WEEK OF SEPT. 9TH", "specialPermissionDropCode": null, "comments": [], "crossListedSections": [], "legendKey": null, "meetingTimes": [{"campusName": "BUSCH", "startTime": "0840", "meetingDay": "W", "meetingModeDesc": "LAB", "roomNumber": "143", "campusLocation": "2", "buildingCode": "DOO", "pmCode": "A", "baClassHours": null, "campusAbbrev": "BUS", "endTime": "1140", "meetingModeCode": "05"}], "specialPermissionAddCode": null, "instructors": [], "printed": "N", "examCode": "A", "campusCode": "NB", "stopPoint": 18, "sectionEligibility": "JUNIORS AND SENIORS ", "sessionDatePrintIndicator": "Y", "openStatus": true}], "subject": "146"}, {"unitNotes": null, "courseDescription": null, "subjectNotes": null, "coreCodes": [], "courseNotes": null, "title": "SYSTEMS PHYSIOLOGY", "supplementCode": "  ", "subjectGroupNotes": null, "courseNumber": "356", "campusCode": "NB", "synopsisUrl": "http://biology.rutgers.edu/biological-sciences/courses#cbn", "preReqNotes": "(01:119:116  and 01:119:116  and 01:160:162  and 01:160:171 ) <em> OR </em> (01:119:116  and 01:119:116  and 01:160:164  and 01:160:171 ) <em> OR </em> (01:119:102  and 01:119:102  and 01:160:162  and 01:160:171 ) <em> OR </em> (01:119:102  and 01:119:102  and 01:160:164  and 01:160:171 )", "openSections": 0, "credits": 3, "offeringUnitCode": "01", "expandedTitle": null, "offeringUnitTitle": null, "sections": [{"minors": [], "sessionDates": null, "honorPrograms": [], "number": "01", "unitMajors": [], "subtitle": null, "specialPermissionDropCodeDescription": null, "specialPermissionAddCodeDescription": null, "subtopic": null, "majors": [], "index": "24135", "sectionNotes": "PREREQS: 01:119:101-102 AND160:162 AND 160:171 OR EQUVALENT", "specialPermissionDropCode": null, "comments": [{"code": "35", "description": "See online schedule for prereqs"}], "crossListedSections": [], "legendKey": null, "meetingTimes": [{"campusName": "DOUGLAS/COOK", "startTime": "0915", "meetingDay": "M", "meetingModeDesc": "LEC", "roomNumber": "138", "campusLocation": "4", "buildingCode": "HCK", "pmCode": "A", "baClassHours": null, "campusAbbrev": "D/C", "endTime": "1035", "meetingModeCode": "02"}, {"campusName": "DOUGLAS/COOK", "startTime": "0915", "meetingDay": "TH", "meetingModeDesc": "LEC", "roomNumber": "138", "campusLocation": "4", "buildingCode": "HCK", "pmCode": "A", "baClassHours": null, "campusAbbrev": "D/C", "endTime": "1035", "meetingModeCode": "02"}], "specialPermissionAddCode": null, "instructors": [{"name": "GOLFETI, R."}], "printed": "Y", "examCode": "C", "campusCode": "NB", "stopPoint": 0, "sectionEligibility": "JUNIORS AND SENIORS ", "sessionDatePrintIndicator": "Y", "openStatus": false}], "subject": "146"}, {"unitNotes": null, "courseDescription": null, "subjectNotes": null, "coreCodes": [], "courseNotes": "ALL SYSTEM PHYSIOLOGY LABS WILL BEGIN THE WEEK OF SEPTEMBER 9TH.", "title": "SYSTEMS PHYSIOL LAB", "supplementCode": "  ", "subjectGroupNotes": null, "courseNumber": "357", "campusCode": "NB", "synopsisUrl": "http://biology.rutgers.edu/biological-sciences/courses#cbn", "preReqNotes": "(01:119:117 )<em> OR </em>(01:119:102 )", "openSections": 4, "credits": 1, "offeringUnitCode": "01", "expandedTitle": null, "offeringUnitTitle": null, "sections": [{"minors": [], "sessionDates": null, "honorPrograms": [], "number": "01", "unitMajors": [], "subtitle": null, "specialPermissionDropCodeDescription": null, "specialPermissionAddCodeDescription": null, "subtopic": null, "majors": [], "index": "24143", "sectionNotes": "PRE OR COREQ: 01:146:356", "specialPermissionDropCode": null, "comments": [], "crossListedSections": [], "legendKey": null, "meetingTimes": [{"campusName": "BUSCH", "startTime": "0840", "meetingDay": "T", "meetingModeDesc": "LAB", "roomNumber": "B137", "campusLocation": "2", "buildingCode": "NH", "pmCode": "A", "baClassHours": null, "campusAbbrev": "BUS", "endTime": "1140", "meetingModeCode": "05"}], "specialPermissionAddCode": null, "instructors": [{"name": "MERRILL,G"}], "printed": "Y", "examCode": "A", "campusCode": "NB", "stopPoint": 16, "sectionEligibility": null, "sessionDatePrintIndicator": "Y", "openStatus": true}, {"minors": [], "sessionDates": null, "honorPrograms": [], "number": "02", "unitMajors": [], "subtitle": null, "specialPermissionDropCodeDescription": null, "specialPermissionAddCodeDescription": null, "subtopic": null, "majors": [], "index": "24144", "sectionNotes": "PRE OR CO-REQ: 01:146:356", "specialPermissionDropCode": null, "comments": [], "crossListedSections": [], "legendKey": null, "meetingTimes": [{"campusName": "BUSCH", "startTime": "0140", "meetingDay": "T", "meetingModeDesc": "LAB", "roomNumber": "B137", "campusLocation": "2", "buildingCode": "NH", "pmCode": "P", "baClassHours": null, "campusAbbrev": "BUS", "endTime": "0440", "meetingModeCode": "05"}], "specialPermissionAddCode": null, "instructors": [], "printed": "Y", "examCode": "A", "campusCode": "NB", "stopPoint": 0, "sectionEligibility": null, "sessionDatePrintIndicator": "Y", "openStatus": false}, {"minors": [], "sessionDates": null, "honorPrograms": [], "number": "04", "unitMajors": [], "subtitle": null, "specialPermissionDropCodeDescription": null, "specialPermissionAddCodeDescription": null, "subtopic": null, "majors": [], "index": "24146", "sectionNotes": "PRE OR CO-REQ: 01:146:356", "specialPermissionDropCode": null, "comments": [], "crossListedSections": [], "legendKey": null, "meetingTimes": [{"campusName": "BUSCH", "startTime": "0840", "meetingDay": "W", "meetingModeDesc": "LAB", "roomNumber": "B137", "campusLocation": "2", "buildingCode": "NH", "pmCode": "A", "baClassHours": null, "campusAbbrev": "BUS", "endTime": "1140", "meetingModeCode": "05"}], "specialPermissionAddCode": null, "instructors": [], "printed": "Y", "examCode": "A", "campusCode": "NB", "stopPoint": 16, "sectionEligibility": null, "sessionDatePrintIndicator": "Y", "openStatus": false}, {"minors": [], "sessionDates": null, "honorPrograms": [], "number": "05", "unitMajors": [], "subtitle": null, "specialPermissionDropCodeDescription": null, "specialPermissionAddCodeDescription": null, "subtopic": null, "majors": [], "index": "24147", "sectionNotes": "PRE OR CO-REQ: 01:146:356", "specialPermissionDropCode": null, "comments": [], "crossListedSections": [], "legendKey": null, "meetingTimes": [{"campusName": "BUSCH", "startTime": "0140", "meetingDay": "W", "meetingModeDesc": "LAB", "roomNumber": "B137", "campusLocation": "2", "buildingCode": "NH", "pmCode": "P", "baClassHours": null, "campusAbbrev": "BUS", "endTime": "0440", "meetingModeCode": "05"}], "specialPermissionAddCode": null, "instructors": [], "printed": "Y", "examCode": "A", "campusCode": "NB", "stopPoint": 16, "sectionEligibility": null, "sessionDatePrintIndicator": "Y", "openStatus": false}, {"minors": [], "sessionDates": null, "honorPrograms": [], "number": "07", "unitMajors": [], "subtitle": null, "specialPermissionDropCodeDescription": null, "specialPermissionAddCodeDescription": null, "subtopic": null, "majors": [], "index": "24149", "sectionNotes": "PRE OR CO-REQ: 01:146:356", "specialPermissionDropCode": null, "comments": [], "crossListedSections": [], "legendKey": null, "meetingTimes": [{"campusName": "BUSCH", "startTime": "0840", "meetingDay": "TH", "meetingModeDesc": "LAB", "roomNumber": "B137", "campusLocation": "2", "buildingCode": "NH", "pmCode": "A", "baClassHours": null, "campusAbbrev": "BUS", "endTime": "1140", "meetingModeCode": "05"}], "specialPermissionAddCode": null, "instructors": [], "printed": "Y", "examCode": "A", "campusCode": "NB", "stopPoint": 16, "sectionEligibility": null, "sessionDatePrintIndicator": "Y", "openStatus": true}, {"minors": [], "sessionDates": null, "honorPrograms": [], "number": "08", "unitMajors": [], "subtitle": null, "specialPermissionDropCodeDescription": null, "specialPermissionAddCodeDescription": null, "subtopic": null, "majors": [], "index": "24150", "sectionNotes": "PRE OR CO-REQ: 01:146:356", "specialPermissionDropCode": null, "comments": [], "crossListedSections": [], "legendKey": null, "meetingTimes": [{"campusName": "BUSCH", "startTime": "0140", "meetingDay": "TH", "meetingModeDesc": "LAB", "roomNumber": "B137", "campusLocation": "2", "buildingCode": "NH", "pmCode": "P", "baClassHours": null, "campusAbbrev": "BUS", "endTime": "0440", "meetingModeCode": "05"}], "specialPermissionAddCode": null, "instructors": [], "printed": "Y", "examCode": "A", "campusCode": "NB", "stopPoint": 16, "sectionEligibility": null, "sessionDatePrintIndicator": "Y", "openStatus": false}, {"minors": [], "sessionDates": null, "honorPrograms": [], "number": "10", "unitMajors": [], "subtitle": null, "specialPermissionDropCodeDescription": null, "specialPermissionAddCodeDescription": null, "subtopic": null, "majors": [], "index": "24152", "sectionNotes": "PRE OR CO-REQ: 01:146:356", "specialPermissionDropCode": null, "comments": [], "crossListedSections": [], "legendKey": null, "meetingTimes": [{"campusName": "BUSCH", "startTime": "0840", "meetingDay": "F", "meetingModeDesc": "LAB", "roomNumber": "B137", "campusLocation": "2", "buildingCode": "NH", "pmCode": "A", "baClassHours": null, "campusAbbrev": "BUS", "endTime": "1140", "meetingModeCode": "05"}], "specialPermissionAddCode": null, "instructors": [], "printed": "Y", "examCode": "A", "campusCode": "NB", "stopPoint": 16, "sectionEligibility": null, "sessionDatePrintIndicator": "Y", "openStatus": true}, {"minors": [], "sessionDates": null, "honorPrograms": [], "number": "11", "unitMajors": [], "subtitle": null, "specialPermissionDropCodeDescription": null, "specialPermissionAddCodeDescription": null, "subtopic": null, "majors": [], "index": "24462", "sectionNotes": "PRE OR CO-REQ: 01:146:356", "specialPermissionDropCode": null, "comments": [], "crossListedSections": [], "legendKey": null, "meetingTimes": [{"campusName": "BUSCH", "startTime": "0640", "meetingDay": "M", "meetingModeDesc": "LAB", "roomNumber": "B137", "campusLocation": "2", "buildingCode": "NH", "pmCode": "P", "baClassHours": null, "campusAbbrev": "BUS", "endTime": "0930", "meetingModeCode": "05"}], "specialPermissionAddCode": null, "instructors": [], "printed": "Y", "examCode": "A", "campusCode": "NB", "stopPoint": 16, "sectionEligibility": null, "sessionDatePrintIndicator": "Y", "openStatus": false}, {"minors": [], "sessionDates": null, "honorPrograms": [], "number": "12", "unitMajors": [], "subtitle": null, "specialPermissionDropCodeDescription": null, "specialPermissionAddCodeDescription": null, "subtopic": null, "majors": [], "index": "24145", "sectionNotes": "PRE OR CO-REQ: 01:146:356", "specialPermissionDropCode": null, "comments": [], "crossListedSections": [], "legendKey": null, "meetingTimes": [{"campusName": "BUSCH", "startTime": "0640", "meetingDay": "T", "meetingModeDesc": "LAB", "roomNumber": "B137", "campusLocation": "2", "buildingCode": "NH", "pmCode": "P", "baClassHours": null, "campusAbbrev": "BUS", "endTime": "0930", "meetingModeCode": "05"}], "specialPermissionAddCode": null, "instructors": [], "printed": "Y", "examCode": "A", "campusCode": "NB", "stopPoint": 16, "sectionEligibility": null, "sessionDatePrintIndicator": "Y", "openStatus": true}, {"minors": [], "sessionDates": null, "honorPrograms": [], "number": "13", "unitMajors": [], "subtitle": null, "specialPermissionDropCodeDescription": null, "specialPermissionAddCodeDescription": null, "subtopic": null, "majors": [], "index": "24148", "sectionNotes": "PRE OR CO-REQ: 01:146:356", "specialPermissionDropCode": null, "comments": [], "crossListedSections": [], "legendKey": null, "meetingTimes": [{"campusName": "BUSCH", "startTime": "0640", "meetingDay": "W", "meetingModeDesc": "LAB", "roomNumber": "B137", "campusLocation": "2", "buildingCode": "NH", "pmCode": "P", "baClassHours": null, "campusAbbrev": "BUS", "endTime": "0930", "meetingModeCode": "05"}], "specialPermissionAddCode": null, "instructors": [], "printed": "Y", "examCode": "A", "campusCode": "NB", "stopPoint": 16, "sectionEligibility": null, "sessionDatePrintIndicator": "Y", "openStatus": false}, {"minors": [], "sessionDates": null, "honorPrograms": [], "number": "14", "unitMajors": [], "subtitle": null, "specialPermissionDropCodeDescription": null, "specialPermissionAddCodeDescription": null, "subtopic": null, "majors": [], "index": "24151", "sectionNotes": "PRE OR CO-REQ: 01:146:356", "specialPermissionDropCode": null, "comments": [], "crossListedSections": [], "legendKey": null, "meetingTimes": [{"campusName": "BUSCH", "startTime": "0640", "meetingDay": "TH", "meetingModeDesc": "LAB", "roomNumber": "B137", "campusLocation": "2", "buildingCode": "NH", "pmCode": "P", "baClassHours": null, "campusAbbrev": "BUS", "endTime": "0930", "meetingModeCode": "05"}], "specialPermissionAddCode": null, "instructors": [], "printed": "Y", "examCode": "A", "campusCode": "NB", "stopPoint": 15, "sectionEligibility": null, "sessionDatePrintIndicator": "Y", "openStatus": false}], "subject": "146"}, {"unitNotes": null, "courseDescription": null, "subjectNotes": null, "coreCodes": [], "courseNotes": null, "title": "RSH CELL BIO NEUROSC", "supplementCode": "  ", "subjectGroupNotes": null, "courseNumber": "406", "campusCode": "NB", "synopsisUrl": "http://biology.rutgers.edu/biological-sciences/courses#cbn", "preReqNotes": null, "openSections": 0, "credits": null, "offeringUnitCode": "01", "expandedTitle": null, "offeringUnitTitle": null, "sections": [{"minors": [], "sessionDates": null, "honorPrograms": [], "number": "01", "unitMajors": [], "subtitle": null, "specialPermissionDropCodeDescription": null, "specialPermissionAddCodeDescription": "Department staff", "subtopic": null, "majors": [{"code": "146", "isUnitCode": false, "isMajorCode": true}], "index": "25212", "sectionNotes": "OPEN ONLY TO CBN MAJORS", "specialPermissionDropCode": null, "comments": [], "crossListedSections": [], "legendKey": null, "meetingTimes": [{"campusName": null, "startTime": null, "meetingDay": null, "meetingModeDesc": "RSCH-MA", "roomNumber": null, "campusLocation": null, "buildingCode": null, "pmCode": null, "baClassHours": "B", "campusAbbrev": null, "endTime": null, "meetingModeCode": "23"}], "specialPermissionAddCode": "03", "instructors": [], "printed": "Y", "examCode": "A", "campusCode": "NB", "stopPoint": 25, "sectionEligibility": null, "sessionDatePrintIndicator": "Y", "openStatus": false}], "subject": "146"}, {"unitNotes": null, "courseDescription": null, "subjectNotes": null, "coreCodes": [], "courseNotes": null, "title": "RSH CELL BIO NEUROSC", "supplementCode": "  ", "subjectGroupNotes": null, "courseNumber": "407", "campusCode": "NB", "synopsisUrl": "http://biology.rutgers.edu/biological-sciences/courses#cbn", "preReqNotes": null, "openSections": 1, "credits": null, "offeringUnitCode": "01", "expandedTitle": null, "offeringUnitTitle": null, "sections": [{"minors": [], "sessionDates": null, "honorPrograms": [], "number": "01", "unitMajors": [], "subtitle": null, "specialPermissionDropCodeDescription": null, "specialPermissionAddCodeDescription": "Department staff", "subtopic": null, "majors": [{"code": "146", "isUnitCode": false, "isMajorCode": true}], "index": "26530", "sectionNotes": "OPEN ONLY TO CBN MAJORS", "specialPermissionDropCode": null, "comments": [], "crossListedSections": [], "legendKey": null, "meetingTimes": [{"campusName": null, "startTime": null, "meetingDay": null, "meetingModeDesc": "RSCH-MA", "roomNumber": null, "campusLocation": null, "buildingCode": null, "pmCode": null, "baClassHours": "B", "campusAbbrev": null, "endTime": null, "meetingModeCode": "23"}], "specialPermissionAddCode": "03", "instructors": [], "printed": "N", "examCode": "A", "campusCode": "NB", "stopPoint": 25, "sectionEligibility": null, "sessionDatePrintIndicator": "Y", "openStatus": true}], "subject": "146"}, {"unitNotes": null, "courseDescription": null, "subjectNotes": null, "coreCodes": [], "courseNotes": null, "title": "HONORS RESEARCH", "supplementCode": "  ", "subjectGroupNotes": null, "courseNumber": "408", "campusCode": "NB", "synopsisUrl": "http://biology.rutgers.edu/biological-sciences/courses#cbn", "preReqNotes": null, "openSections": 0, "credits": null, "offeringUnitCode": "01", "expandedTitle": null, "offeringUnitTitle": null, "sections": [{"minors": [], "sessionDates": null, "honorPrograms": [{"code": "5"}, {"code": "6"}, {"code": "7"}, {"code": "A"}, {"code": "B"}], "number": "H1", "unitMajors": [], "subtitle": null, "specialPermissionDropCodeDescription": null, "specialPermissionAddCodeDescription": "Department staff", "subtopic": null, "majors": [], "index": "25797", "sectionNotes": "PREREQ: OPEN ONLY TO SENIORCBN HONOR STUDENTS", "specialPermissionDropCode": null, "comments": [{"code": "87", "description": "For Honors Students only"}], "crossListedSections": [], "legendKey": null, "meetingTimes": [{"campusName": null, "startTime": null, "meetingDay": null, "meetingModeDesc": "RSCH-MA", "roomNumber": null, "campusLocation": null, "buildingCode": null, "pmCode": null, "baClassHours": "B", "campusAbbrev": null, "endTime": null, "meetingModeCode": "23"}], "specialPermissionAddCode": "03", "instructors": [], "printed": "Y", "examCode": "A", "campusCode": "NB", "stopPoint": 25, "sectionEligibility": "SENIORS ONLY ", "sessionDatePrintIndicator": "Y", "openStatus": false}], "subject": "146"}, {"unitNotes": null, "courseDescription": null, "subjectNotes": null, "coreCodes": [], "courseNotes": null, "title": "HONORS RESEARCH", "supplementCode": "  ", "subjectGroupNotes": null, "courseNumber": "409", "campusCode": "NB", "synopsisUrl": "http://biology.rutgers.edu/biological-sciences/courses#cbn", "preReqNotes": null, "openSections": 1, "credits": null, "offeringUnitCode": "01", "expandedTitle": null, "offeringUnitTitle": null, "sections": [{"minors": [], "sessionDates": null, "honorPrograms": [{"code": "A"}, {"code": "6"}, {"code": "7"}, {"code": "B"}, {"code": "5"}], "number": "H1", "unitMajors": [], "subtitle": null, "specialPermissionDropCodeDescription": null, "specialPermissionAddCodeDescription": "Department staff", "subtopic": null, "majors": [{"code": "146", "isUnitCode": false, "isMajorCode": true}], "index": "26531", "sectionNotes": "OPEN ONLY TO SENIOR CBN HONORSSTUDENTS", "specialPermissionDropCode": null, "comments": [{"code": "87", "description": "For Honors Students only"}], "crossListedSections": [], "legendKey": null, "meetingTimes": [{"campusName": null, "startTime": null, "meetingDay": null, "meetingModeDesc": "RSCH-MA", "roomNumber": null, "campusLocation": null, "buildingCode": null, "pmCode": null, "baClassHours": "B", "campusAbbrev": null, "endTime": null, "meetingModeCode": "23"}], "specialPermissionAddCode": "03", "instructors": [], "printed": "N", "examCode": "A", "campusCode": "NB", "stopPoint": 25, "sectionEligibility": "SENIORS ONLY ", "sessionDatePrintIndicator": "Y", "openStatus": true}], "subject": "146"}, {"unitNotes": null, "courseDescription": null, "subjectNotes": null, "coreCodes": [], "courseNotes": null, "title": "ADV NEUROBIOLOGY I", "supplementCode": "  ", "subjectGroupNotes": null, "courseNumber": "445", "campusCode": "NB", "synopsisUrl": "http://biology.rutgers.edu/biological-sciences/courses#cbn", "preReqNotes": "(01:146:245  and 01:146:270  and 01:119:117  and 01:119:117 ) <em> OR </em> (01:146:245  and 01:146:270  and 01:119:102  and 01:119:102 )", "openSections": 0, "credits": 4, "offeringUnitCode": "01", "expandedTitle": null, "offeringUnitTitle": null, "sections": [{"minors": [], "sessionDates": null, "honorPrograms": [], "number": "01", "unitMajors": [], "subtitle": null, "specialPermissionDropCodeDescription": null, "specialPermissionAddCodeDescription": null, "subtopic": null, "majors": [], "index": "25283", "sectionNotes": "PREREQS: 01:146:245 AND 146:270", "specialPermissionDropCode": null, "comments": [{"code": "35", "description": "See online schedule for prereqs"}], "crossListedSections": [{"subjectCode": "710", "supplementCode": "  ", "registrationIndex": "25456", "offeringUnitCode": "16", "primaryRegistrationIndex": "25283", "courseNumber": "555", "offeringUnitCampus": "NB", "sectionNumber": "01"}], "legendKey": null, "meetingTimes": [{"campusName": "BUSCH", "startTime": "0640", "meetingDay": "M", "meetingModeDesc": "LEC", "roomNumber": "117", "campusLocation": "2", "buildingCode": "SEC", "pmCode": "P", "baClassHours": null, "campusAbbrev": "BUS", "endTime": "0930", "meetingModeCode": "02"}, {"campusName": "BUSCH", "startTime": "0640", "meetingDay": "W", "meetingModeDesc": "LEC", "roomNumber": "117", "campusLocation": "2", "buildingCode": "SEC", "pmCode": "P", "baClassHours": null, "campusAbbrev": "BUS", "endTime": "0930", "meetingModeCode": "02"}], "specialPermissionAddCode": null, "instructors": [{"name": "PLUMMER,M"}], "printed": "Y", "examCode": "S", "campusCode": "NB", "stopPoint": 70, "sectionEligibility": null, "sessionDatePrintIndicator": "Y", "openStatus": false}], "subject": "146"}, {"unitNotes": null, "courseDescription": null, "subjectNotes": null, "coreCodes": [], "courseNotes": null, "title": "TOP CELL BIO NEUROSC", "supplementCode": "  ", "subjectGroupNotes": null, "courseNumber": "464", "campusCode": "NB", "synopsisUrl": "http://biology.rutgers.edu/biological-sciences/courses#cbn", "preReqNotes": "(01:146:245 )<em> AND </em>(01:146:270 )", "openSections": 1, "credits": 3, "offeringUnitCode": "01", "expandedTitle": null, "offeringUnitTitle": null, "sections": [{"minors": [], "sessionDates": null, "honorPrograms": [], "number": "01", "unitMajors": [], "subtitle": null, "specialPermissionDropCodeDescription": null, "specialPermissionAddCodeDescription": null, "subtopic": null, "majors": [], "index": "25469", "sectionNotes": null, "specialPermissionDropCode": null, "comments": [{"code": "35", "description": "See online schedule for prereqs"}], "crossListedSections": [], "legendKey": null, "meetingTimes": [{"campusName": "BUSCH", "startTime": "0500", "meetingDay": "TH", "meetingModeDesc": "LEC", "roomNumber": "D251", "campusLocation": "2", "buildingCode": "NH", "pmCode": "P", "baClassHours": null, "campusAbbrev": "BUS", "endTime": "0620", "meetingModeCode": "02"}, {"campusName": "BUSCH", "startTime": "0500", "meetingDay": "T", "meetingModeDesc": "LEC", "roomNumber": "D251", "campusLocation": "2", "buildingCode": "NH", "pmCode": "P", "baClassHours": null, "campusAbbrev": "BUS", "endTime": "0620", "meetingModeCode": "02"}], "specialPermissionAddCode": null, "instructors": [{"name": "YOUNG,W/GRUMET"}], "printed": "Y", "examCode": "O", "campusCode": "NB", "stopPoint": 20, "sectionEligibility": "JUNIORS AND SENIORS ", "sessionDatePrintIndicator": "Y", "openStatus": true}], "subject": "146"}, {"unitNotes": null, "courseDescription": null, "subjectNotes": null, "coreCodes": [], "courseNotes": null, "title": "ADV CELL BIOLOGY", "supplementCode": "  ", "subjectGroupNotes": null, "courseNumber": "470", "campusCode": "NB", "synopsisUrl": "http://biology.rutgers.edu/biological-sciences/courses#cbn", "preReqNotes": "((01:146:270  and 01:119:117 ) or (01:119:102 ))", "openSections": 1, "credits": 3, "offeringUnitCode": "01", "expandedTitle": null, "offeringUnitTitle": null, "sections": [{"minors": [], "sessionDates": null, "honorPrograms": [], "number": "01", "unitMajors": [], "subtitle": null, "specialPermissionDropCodeDescription": null, "specialPermissionAddCodeDescription": null, "subtopic": null, "majors": [{"code": "146", "isUnitCode": false, "isMajorCode": true}], "index": "25020", "sectionNotes": null, "specialPermissionDropCode": null, "comments": [{"code": "35", "description": "See online schedule for prereqs"}], "crossListedSections": [{"subjectCode": "148", "supplementCode": "  ", "registrationIndex": "22984", "offeringUnitCode": "16", "primaryRegistrationIndex": "25020", "courseNumber": "514", "offeringUnitCampus": "NB", "sectionNumber": "01"}], "legendKey": null, "meetingTimes": [{"campusName": "BUSCH", "startTime": "0840", "meetingDay": "M", "meetingModeDesc": "LEC", "roomNumber": "118", "campusLocation": "2", "buildingCode": "SEC", "pmCode": "A", "baClassHours": null, "campusAbbrev": "BUS", "endTime": "1000", "meetingModeCode": "02"}, {"campusName": "BUSCH", "startTime": "0840", "meetingDay": "TH", "meetingModeDesc": "LEC", "roomNumber": "118", "campusLocation": "2", "buildingCode": "SEC", "pmCode": "A", "baClassHours": null, "campusAbbrev": "BUS", "endTime": "1000", "meetingModeCode": "02"}], "specialPermissionAddCode": null, "instructors": [{"name": "HART, R."}], "printed": "Y", "examCode": "C", "campusCode": "NB", "stopPoint": 110, "sectionEligibility": "SENIORS ONLY ", "sessionDatePrintIndicator": "Y", "openStatus": true}], "subject": "146"}]