[{"unitNotes": null, "courseDescription": null, "subjectNotes": null, "coreCodes": [{"code": "HST", "description": "[Historical Analysis]", "effective": "20119", "course": "110", "supplement": null, "unit": "01", "subject": "506"}], "courseNotes": null, "title": "AGE EUR GLOBAL EXPAN", "supplementCode": "  ", "subjectGroupNotes": null, "courseNumber": "110", "campusCode": "NB", "synopsisUrl": "http://history.rutgers.edu/undergraduate/undergraduate-courses/fall-2013-classes", "preReqNotes": null, "openSections": 1, "credits": 3, "offeringUnitCode": "01", "expandedTitle": "AGE OF EUROPEAN GLOBAL EXPANSION                                                ", "offeringUnitTitle": null, "sections": [{"minors": [], "sessionDates": null, "honorPrograms": [], "number": "01", "unitMajors": [], "subtitle": null, "specialPermissionDropCodeDescription": null, "specialPermissionAddCodeDescription": null, "subtopic": null, "majors": [], "index": "27206", "sectionNotes": null, "specialPermissionDropCode": null, "comments": [], "crossListedSections": [], "legendKey": null, "meetingTimes": [{"campusName": "COLLEGE AVENUE", "startTime": "1130", "meetingDay": "M", "meetingModeDesc": "LEC", "roomNumber": "211", "campusLocation": "1", "buildingCode": "VD", "pmCode": "A", "baClassHours": null, "campusAbbrev": "CAC", "endTime": "1250", "meetingModeCode": "02"}, {"campusName": "COLLEGE AVENUE", "startTime": "1130", "meetingDay": "TH", "meetingModeDesc": "LEC", "roomNumber": "211", "campusLocation": "1", "buildingCode": "VD", "pmCode": "A", "baClassHours": null, "campusAbbrev": "CAC", "endTime": "1250", "meetingModeCode": "02"}], "specialPermissionAddCode": null, "instructors": [{"name": "SMITH, B."}], "printed": "Y", "examCode": "C", "campusCode": "NB", "stopPoint": 75, "sectionEligibility": null, "sessionDatePrintIndicator": "Y", "openStatus": true}], "subject": "506"}, {"unitNotes": null, "courseDescription": null, "subjectNotes": null, "coreCodes": [{"code": "HST", "description": "[Historical Analysis]", "effective": "20139", "course": "201", "supplement": null, "unit": "01", "subject": "506"}, {"code": "SCL", "description": "[Social Analysis]", "effective": "20139", "course": "201", "supplement": null, "unit": "01", "subject": "506"}], "courseNotes": null, "title": "20TH CENT HIST-1945", "supplementCode": "  ", "subjectGroupNotes": null, "courseNumber": "201", "campusCode": "NB", "synopsisUrl": "http://history.rutgers.edu/undergraduate/undergraduate-courses/fall-2013-classes", "preReqNotes": null, "openSections": 1, "credits": 3, "offeringUnitCode": "01", "expandedTitle": null, "offeringUnitTitle": null, "sections": [{"minors": [], "sessionDates": null, "honorPrograms": [], "number": "01", "unitMajors": [], "subtitle": null, "specialPermissionDropCodeDescription": null, "specialPermissionAddCodeDescription": null, "subtopic": null, "majors": [], "index": "37290", "sectionNotes": "W6  HH A4 EXTRA DISCUSSION ROOM", "specialPermissionDropCode": null, "comments": [], "crossListedSections": [], "legendKey": null, "meetingTimes": [{"campusName": "COLLEGE AVENUE", "startTime": "0430", "meetingDay": "M", "meetingModeDesc": "LEC", "roomNumber": "211", "campusLocation": "1", "buildingCode": "VD", "pmCode": "P", "baClassHours": null, "campusAbbrev": "CAC", "endTime": "0550", "meetingModeCode": "02"}, {"campusName": "COLLEGE AVENUE", "startTime": "0430", "meetingDay": "W", "meetingModeDesc": "LEC", "roomNumber": "211", "campusLocation": "1", "buildingCode": "VD", "pmCode": "P", "baClassHours": null, "campusAbbrev": "CAC", "endTime": "0550", "meetingModeCode": "02"}], "specialPermissionAddCode": null, "instructors": [{"name": "ADAS"}], "printed": "Y", "examCode": "C", "campusCode": "NB", "stopPoint": 75, "sectionEligibility": null, "sessionDatePrintIndicator": "Y", "openStatus": true}], "subject": "506"}, {"unitNotes": null, "courseDescription": null, "subjectNotes": null, "coreCodes": [{"code": "HST", "description": "[Historical Analysis]", "effective": "20139", "course": "202", "supplement": null, "unit": "01", "subject": "506"}, {"code": "SCL", "description": "[Social Analysis]", "effective": "20139", "course": "202", "supplement": null, "unit": "01", "subject": "506"}], "courseNotes": null, "title": "20TH CENT HIST 1945+", "supplementCode": "  ", "subjectGroupNotes": null, "courseNumber": "202", "campusCode": "NB", "synopsisUrl": "http://history.rutgers.edu/undergraduate/undergraduate-courses/fall-2013-classes", "preReqNotes": null, "openSections": 0, "credits": 3, "offeringUnitCode": "01", "expandedTitle": "TWENTIETH-CENTURY GLOBAL HISTORY FROM 1945                                      ", "offeringUnitTitle": null, "sections": [{"minors": [], "sessionDates": null, "honorPrograms": [], "number": "01", "unitMajors": [], "subtitle": null, "specialPermissionDropCodeDescription": null, "specialPermissionAddCodeDescription": null, "subtopic": null, "majors": [], "index": "38358", "sectionNotes": null, "specialPermissionDropCode": null, "comments": [], "crossListedSections": [], "legendKey": null, "meetingTimes": [{"campusName": "COLLEGE AVENUE", "startTime": "0250", "meetingDay": "T", "meetingModeDesc": "LEC", "roomNumber": "B6", "campusLocation": "1", "buildingCode": "HH", "pmCode": "P", "baClassHours": null, "campusAbbrev": "CAC", "endTime": "0410", "meetingModeCode": "02"}, {"campusName": "COLLEGE AVENUE", "startTime": "0250", "meetingDay": "TH", "meetingModeDesc": "LEC", "roomNumber": "B6", "campusLocation": "1", "buildingCode": "HH", "pmCode": "P", "baClassHours": null, "campusAbbrev": "CAC", "endTime": "0410", "meetingModeCode": "02"}], "specialPermissionAddCode": null, "instructors": [{"name": "FEIN"}], "printed": "Y", "examCode": "C", "campusCode": "NB", "stopPoint": 35, "sectionEligibility": null, "sessionDatePrintIndicator": "Y", "openStatus": false}], "subject": "506"}, {"unitNotes": null, "courseDescription": null, "subjectNotes": null, "coreCodes": [{"code": "HST", "description": "[Historical Analysis]", "effective": "20119", "course": "203", "supplement": null, "unit": "01", "subject": "506"}], "courseNotes": null, "title": "HIST OF THE PACIFIC", "supplementCode": "  ", "subjectGroupNotes": null, "courseNumber": "203", "campusCode": "NB", "synopsisUrl": "http://history.rutgers.edu/undergraduate/undergraduate-courses/fall-2013-classes", "preReqNotes": null, "openSections": 1, "credits": 3, "offeringUnitCode": "01", "expandedTitle": null, "offeringUnitTitle": null, "sections": [{"minors": [], "sessionDates": null, "honorPrograms": [], "number": "01", "unitMajors": [], "subtitle": null, "specialPermissionDropCodeDescription": null, "specialPermissionAddCodeDescription": null, "subtopic": null, "majors": [], "index": "28189", "sectionNotes": null, "specialPermissionDropCode": null, "comments": [], "crossListedSections": [], "legendKey": null, "meetingTimes": [{"campusName": "COLLEGE AVENUE", "startTime": "0950", "meetingDay": "F", "meetingModeDesc": "LEC", "roomNumber": "212", "campusLocation": "1", "buildingCode": "MU", "pmCode": "A", "baClassHours": null, "campusAbbrev": "CAC", "endTime": "1110", "meetingModeCode": "02"}, {"campusName": "COLLEGE AVENUE", "startTime": "0950", "meetingDay": "T", "meetingModeDesc": "LEC", "roomNumber": "212", "campusLocation": "1", "buildingCode": "MU", "pmCode": "A", "baClassHours": null, "campusAbbrev": "CAC", "endTime": "1110", "meetingModeCode": "02"}], "specialPermissionAddCode": null, "instructors": [{"name": "MATSUDA"}], "printed": "Y", "examCode": "C", "campusCode": "NB", "stopPoint": 80, "sectionEligibility": null, "sessionDatePrintIndicator": "Y", "openStatus": true}], "subject": "506"}, {"unitNotes": null, "courseDescription": null, "subjectNotes": null, "coreCodes": [{"code": "HST", "description": "[Historical Analysis]", "effective": "20139", "course": "251", "supplement": null, "unit": "01", "subject": "506"}], "courseNotes": null, "title": "SCIENCE & SOCIETY", "supplementCode": "  ", "subjectGroupNotes": null, "courseNumber": "251", "campusCode": "NB", "synopsisUrl": "http://history.rutgers.edu/undergraduate/undergraduate-courses/fall-2013-classes", "preReqNotes": null, "openSections": 1, "credits": 3, "offeringUnitCode": "01", "expandedTitle": null, "offeringUnitTitle": null, "sections": [{"minors": [], "sessionDates": null, "honorPrograms": [], "number": "01", "unitMajors": [], "subtitle": null, "specialPermissionDropCodeDescription": null, "specialPermissionAddCodeDescription": null, "subtopic": null, "majors": [], "index": "36781", "sectionNotes": null, "specialPermissionDropCode": null, "comments": [], "crossListedSections": [], "legendKey": null, "meetingTimes": [{"campusName": "COLLEGE AVENUE", "startTime": "0430", "meetingDay": "M", "meetingModeDesc": "LEC", "roomNumber": "A5", "campusLocation": "1", "buildingCode": "CA", "pmCode": "P", "baClassHours": null, "campusAbbrev": "CAC", "endTime": "0550", "meetingModeCode": "02"}, {"campusName": "COLLEGE AVENUE", "startTime": "0430", "meetingDay": "W", "meetingModeDesc": "LEC", "roomNumber": "A5", "campusLocation": "1", "buildingCode": "CA", "pmCode": "P", "baClassHours": null, "campusAbbrev": "CAC", "endTime": "0550", "meetingModeCode": "02"}], "specialPermissionAddCode": null, "instructors": [{"name": "LESCH"}], "printed": "Y", "examCode": "C", "campusCode": "NB", "stopPoint": 50, "sectionEligibility": null, "sessionDatePrintIndicator": "Y", "openStatus": true}], "subject": "506"}, {"unitNotes": null, "courseDescription": null, "subjectNotes": null, "coreCodes": [{"code": "HST", "description": "[Historical Analysis]", "effective": "20119", "course": "271", "supplement": null, "unit": "01", "subject": "506"}], "courseNotes": null, "title": "JEWISH SOC&CULTURE I", "supplementCode": "  ", "subjectGroupNotes": null, "courseNumber": "271", "campusCode": "NB", "synopsisUrl": "http://history.rutgers.edu/undergraduate/undergraduate-courses/fall-2013-classes", "preReqNotes": null, "openSections": 1, "credits": 3, "offeringUnitCode": "01", "expandedTitle": null, "offeringUnitTitle": null, "sections": [{"minors": [], "sessionDates": null, "honorPrograms": [], "number": "01", "unitMajors": [], "subtitle": null, "specialPermissionDropCodeDescription": null, "specialPermissionAddCodeDescription": null, "subtopic": null, "majors": [], "index": "24185", "sectionNotes": null, "specialPermissionDropCode": null, "comments": [], "crossListedSections": [{"subjectCode": "563", "supplementCode": "  ", "registrationIndex": "24008", "offeringUnitCode": "01", "primaryRegistrationIndex": "24185", "courseNumber": "201", "offeringUnitCampus": "NB", "sectionNumber": "01"}, {"subjectCode": "563", "supplementCode": "  ", "registrationIndex": "31426", "offeringUnitCode": "16", "primaryRegistrationIndex": "24185", "courseNumber": "501", "offeringUnitCampus": "NB", "sectionNumber": "01"}, {"subjectCode": "685", "supplementCode": "  ", "registrationIndex": "27107", "offeringUnitCode": "01", "primaryRegistrationIndex": "24185", "courseNumber": "208", "offeringUnitCampus": "NB", "sectionNumber": "01"}], "legendKey": null, "meetingTimes": [{"campusName": "COLLEGE AVENUE", "startTime": "0110", "meetingDay": "W", "meetingModeDesc": "LEC", "roomNumber": "A7", "campusLocation": "1", "buildingCode": "HH", "pmCode": "P", "baClassHours": null, "campusAbbrev": "CAC", "endTime": "0230", "meetingModeCode": "02"}, {"campusName": "COLLEGE AVENUE", "startTime": "0110", "meetingDay": "M", "meetingModeDesc": "LEC", "roomNumber": "A7", "campusLocation": "1", "buildingCode": "HH", "pmCode": "P", "baClassHours": null, "campusAbbrev": "CAC", "endTime": "0230", "meetingModeCode": "02"}], "specialPermissionAddCode": null, "instructors": [{"name": "RENDSBURG"}], "printed": "Y", "examCode": "C", "campusCode": "NB", "stopPoint": 20, "sectionEligibility": null, "sessionDatePrintIndicator": "Y", "openStatus": true}], "subject": "506"}, {"unitNotes": null, "courseDescription": null, "subjectNotes": null, "coreCodes": [], "courseNotes": null, "title": "TOPICS IN HISTORY", "supplementCode": "  ", "subjectGroupNotes": null, "courseNumber": "291", "campusCode": "NB", "synopsisUrl": "http://history.rutgers.edu/undergraduate/undergraduate-courses/fall-2013-classes", "preReqNotes": null, "openSections": 1, "credits": 3, "offeringUnitCode": "01", "expandedTitle": null, "offeringUnitTitle": null, "sections": [{"minors": [], "sessionDates": null, "honorPrograms": [], "number": "03", "unitMajors": [], "subtitle": null, "specialPermissionDropCodeDescription": null, "specialPermissionAddCodeDescription": "Department staff", "subtopic": null, "majors": [], "index": "33010", "sectionNotes": "MEETS AT STUDENT SUPPORT SERVICECONFERENCE ROOM", "specialPermissionDropCode": null, "comments": [], "crossListedSections": [], "legendKey": null, "meetingTimes": [{"campusName": null, "startTime": null, "meetingDay": null, "meetingModeDesc": "LEC", "roomNumber": null, "campusLocation": null, "buildingCode": null, "pmCode": null, "baClassHours": "B", "campusAbbrev": null, "endTime": null, "meetingModeCode": "02"}], "specialPermissionAddCode": "03", "instructors": [{"name": "RODEN"}, {"name": "BARRY"}], "printed": "Y", "examCode": "A", "campusCode": "NB", "stopPoint": 20, "sectionEligibility": null, "sessionDatePrintIndicator": "Y", "openStatus": true}], "subject": "506"}, {"unitNotes": null, "courseDescription": null, "subjectNotes": null, "coreCodes": [], "courseNotes": null, "title": "DISEASE IN HISTORY", "supplementCode": "  ", "subjectGroupNotes": null, "courseNumber": "321", "campusCode": "NB", "synopsisUrl": "http://history.rutgers.edu/undergraduate/undergraduate-courses/fall-2013-classes", "preReqNotes": null, "openSections": 0, "credits": 3, "offeringUnitCode": "01", "expandedTitle": null, "offeringUnitTitle": null, "sections": [{"minors": [], "sessionDates": null, "honorPrograms": [], "number": "01", "unitMajors": [], "subtitle": null, "specialPermissionDropCodeDescription": null, "specialPermissionAddCodeDescription": null, "subtopic": null, "majors": [], "index": "36780", "sectionNotes": null, "specialPermissionDropCode": null, "comments": [], "crossListedSections": [], "legendKey": null, "meetingTimes": [{"campusName": "COLLEGE AVENUE", "startTime": "0110", "meetingDay": "M", "meetingModeDesc": "LEC", "roomNumber": "A2", "campusLocation": "1", "buildingCode": "HH", "pmCode": "P", "baClassHours": null, "campusAbbrev": "CAC", "endTime": "0230", "meetingModeCode": "02"}, {"campusName": "COLLEGE AVENUE", "startTime": "0110", "meetingDay": "W", "meetingModeDesc": "LEC", "roomNumber": "A2", "campusLocation": "1", "buildingCode": "HH", "pmCode": "P", "baClassHours": null, "campusAbbrev": "CAC", "endTime": "0230", "meetingModeCode": "02"}], "specialPermissionAddCode": null, "instructors": [{"name": "LESCH"}], "printed": "Y", "examCode": "C", "campusCode": "NB", "stopPoint": 40, "sectionEligibility": null, "sessionDatePrintIndicator": "Y", "openStatus": false}], "subject": "506"}, {"unitNotes": null, "courseDescription": null, "subjectNotes": null, "coreCodes": [], "courseNotes": null, "title": "IMPERIALISM", "supplementCode": "  ", "subjectGroupNotes": null, "courseNumber": "363", "campusCode": "NB", "synopsisUrl": "http://history.rutgers.edu/undergraduate/undergraduate-courses/fall-2013-classes", "preReqNotes": null, "openSections": 0, "credits": 3, "offeringUnitCode": "01", "expandedTitle": null, "offeringUnitTitle": null, "sections": [{"minors": [], "sessionDates": null, "honorPrograms": [], "number": "01", "unitMajors": [], "subtitle": null, "specialPermissionDropCodeDescription": null, "specialPermissionAddCodeDescription": null, "subtopic": null, "majors": [], "index": "35173", "sectionNotes": null, "specialPermissionDropCode": null, "comments": [], "crossListedSections": [], "legendKey": null, "meetingTimes": [{"campusName": "COLLEGE AVENUE", "startTime": "0250", "meetingDay": "M", "meetingModeDesc": "LEC", "roomNumber": "A5", "campusLocation": "1", "buildingCode": "FH", "pmCode": "P", "baClassHours": null, "campusAbbrev": "CAC", "endTime": "0410", "meetingModeCode": "02"}, {"campusName": "COLLEGE AVENUE", "startTime": "0250", "meetingDay": "W", "meetingModeDesc": "LEC", "roomNumber": "A5", "campusLocation": "1", "buildingCode": "FH", "pmCode": "P", "baClassHours": null, "campusAbbrev": "CAC", "endTime": "0410", "meetingModeCode": "02"}], "specialPermissionAddCode": null, "instructors": [{"name": "IKEYA"}], "printed": "Y", "examCode": "C", "campusCode": "NB", "stopPoint": 50, "sectionEligibility": null, "sessionDatePrintIndicator": "Y", "openStatus": false}], "subject": "506"}, {"unitNotes": null, "courseDescription": null, "subjectNotes": null, "coreCodes": [], "courseNotes": null, "title": "HISTORICAL STUDIES", "supplementCode": "  ", "subjectGroupNotes": null, "courseNumber": "391", "campusCode": "NB", "synopsisUrl": "http://history.rutgers.edu/undergraduate/undergraduate-courses/fall-2013-classes", "preReqNotes": null, "openSections": 1, "credits": 3, "offeringUnitCode": "01", "expandedTitle": null, "offeringUnitTitle": null, "sections": [{"minors": [], "sessionDates": null, "honorPrograms": [], "number": "01", "unitMajors": [], "subtitle": "HUM/ANIMAL RELATN:HIST OF CONTACT ZONES ", "specialPermissionDropCodeDescription": null, "specialPermissionAddCodeDescription": null, "subtopic": null, "majors": [], "index": "31723", "sectionNotes": null, "specialPermissionDropCode": null, "comments": [], "crossListedSections": [{"subjectCode": "070", "supplementCode": "  ", "registrationIndex": "38797", "offeringUnitCode": "01", "primaryRegistrationIndex": "31723", "courseNumber": "302", "offeringUnitCampus": "NB", "sectionNumber": "01"}], "legendKey": null, "meetingTimes": [{"campusName": "DOUGLAS/COOK", "startTime": "0355", "meetingDay": "T", "meetingModeDesc": "LEC", "roomNumber": "122", "campusLocation": "4", "buildingCode": "DAV", "pmCode": "P", "baClassHours": null, "campusAbbrev": "D/C", "endTime": "0515", "meetingModeCode": "02"}, {"campusName": "DOUGLAS/COOK", "startTime": "0355", "meetingDay": "TH", "meetingModeDesc": "LEC", "roomNumber": "122", "campusLocation": "4", "buildingCode": "DAV", "pmCode": "P", "baClassHours": null, "campusAbbrev": "D/C", "endTime": "0515", "meetingModeCode": "02"}], "specialPermissionAddCode": null, "instructors": [{"name": "PARRENAS"}], "printed": "Y", "examCode": "C", "campusCode": "NB", "stopPoint": 30, "sectionEligibility": null, "sessionDatePrintIndicator": "Y", "openStatus": true}], "subject": "506"}, {"unitNotes": null, "courseDescription": null, "subjectNotes": null, "coreCodes": [{"code": "WCd", "description": "[Writing and Communication in a Discipline]", "effective": "20121", "course": "401", "supplement": null, "unit": "01", "subject": "506"}, {"code": "WCr", "description": "[Writing and Communication, Revision]", "effective": "20121", "course": "401", "supplement": null, "unit": "01", "subject": "506"}], "courseNotes": null, "title": "HISTORY SEMINAR", "supplementCode": "  ", "subjectGroupNotes": null, "courseNumber": "401", "campusCode": "NB", "synopsisUrl": "http://history.rutgers.edu/undergraduate/undergraduate-courses/fall-2013-classes", "preReqNotes": null, "openSections": 7, "credits": 3, "offeringUnitCode": "01", "expandedTitle": null, "offeringUnitTitle": null, "sections": [{"minors": [], "sessionDates": null, "honorPrograms": [], "number": "01", "unitMajors": [], "subtitle": "GENDER AND THE US MILITARY              ", "specialPermissionDropCodeDescription": null, "specialPermissionAddCodeDescription": null, "subtopic": null, "majors": [{"code": "514", "isUnitCode": false, "isMajorCode": true}, {"code": "510", "isUnitCode": false, "isMajorCode": true}], "index": "29024", "sectionNotes": null, "specialPermissionDropCode": null, "comments": [], "crossListedSections": [], "legendKey": null, "meetingTimes": [{"campusName": "COLLEGE AVENUE", "startTime": "0950", "meetingDay": "TH", "meetingModeDesc": "SEM", "roomNumber": "211", "campusLocation": "1", "buildingCode": "BH", "pmCode": "A", "baClassHours": null, "campusAbbrev": "CAC", "endTime": "1250", "meetingModeCode": "04"}], "specialPermissionAddCode": null, "instructors": [{"name": "MITTELSTADT"}], "printed": "Y", "examCode": "C", "campusCode": "NB", "stopPoint": 15, "sectionEligibility": "JUNIORS AND SENIORS ", "sessionDatePrintIndicator": "Y", "openStatus": true}, {"minors": [], "sessionDates": null, "honorPrograms": [], "number": "03", "unitMajors": [], "subtitle": "US MILITARY OCCUPATIONS-FOREIGN NATIONS ", "specialPermissionDropCodeDescription": null, "specialPermissionAddCodeDescription": null, "subtopic": null, "majors": [{"code": "510", "isUnitCode": false, "isMajorCode": true}, {"code": "514", "isUnitCode": false, "isMajorCode": true}], "index": "31779", "sectionNotes": null, "specialPermissionDropCode": null, "comments": [], "crossListedSections": [], "legendKey": null, "meetingTimes": [{"campusName": "COLLEGE AVENUE", "startTime": "0250", "meetingDay": "M", "meetingModeDesc": "SEM", "roomNumber": "215", "campusLocation": "1", "buildingCode": "SC", "pmCode": "P", "baClassHours": null, "campusAbbrev": "CAC", "endTime": "0550", "meetingModeCode": "04"}], "specialPermissionAddCode": null, "instructors": [{"name": "FOGLESONG"}], "printed": "Y", "examCode": "C", "campusCode": "NB", "stopPoint": 15, "sectionEligibility": "JUNIORS AND SENIORS ", "sessionDatePrintIndicator": "Y", "openStatus": false}, {"minors": [], "sessionDates": null, "honorPrograms": [], "number": "04", "unitMajors": [], "subtitle": "ASIAN AMERICANS IN THE 20TH CENTURY     ", "specialPermissionDropCodeDescription": null, "specialPermissionAddCodeDescription": null, "subtopic": null, "majors": [{"code": "514", "isUnitCode": false, "isMajorCode": true}, {"code": "510", "isUnitCode": false, "isMajorCode": true}], "index": "30883", "sectionNotes": null, "specialPermissionDropCode": null, "comments": [], "crossListedSections": [], "legendKey": null, "meetingTimes": [{"campusName": "COLLEGE AVENUE", "startTime": "0110", "meetingDay": "T", "meetingModeDesc": "SEM", "roomNumber": "211", "campusLocation": "1", "buildingCode": "BH", "pmCode": "P", "baClassHours": null, "campusAbbrev": "CAC", "endTime": "0410", "meetingModeCode": "04"}], "specialPermissionAddCode": null, "instructors": [{"name": "SCHREPFER"}], "printed": "Y", "examCode": "C", "campusCode": "NB", "stopPoint": 15, "sectionEligibility": "JUNIORS AND SENIORS ", "sessionDatePrintIndicator": "Y", "openStatus": true}, {"minors": [], "sessionDates": null, "honorPrograms": [], "number": "06", "unitMajors": [], "subtitle": "THE SOCIAL & ARCHITECTURAL HISTORY OF RU", "specialPermissionDropCodeDescription": null, "specialPermissionAddCodeDescription": null, "subtopic": null, "majors": [{"code": "514", "isUnitCode": false, "isMajorCode": true}, {"code": "510", "isUnitCode": false, "isMajorCode": true}], "index": "30471", "sectionNotes": null, "specialPermissionDropCode": null, "comments": [], "crossListedSections": [{"subjectCode": "082", "supplementCode": "  ", "registrationIndex": "31688", "offeringUnitCode": "01", "primaryRegistrationIndex": "30471", "courseNumber": "491", "offeringUnitCampus": "NB", "sectionNumber": "04"}], "legendKey": null, "meetingTimes": [{"campusName": "COLLEGE AVENUE", "startTime": "0110", "meetingDay": "W", "meetingModeDesc": "SEM", "roomNumber": "215", "campusLocation": "1", "buildingCode": "SC", "pmCode": "P", "baClassHours": null, "campusAbbrev": "CAC", "endTime": "0410", "meetingModeCode": "04"}], "specialPermissionAddCode": null, "instructors": [{"name": "CLEMENS"}, {"name": "YANNI"}], "printed": "Y", "examCode": "C", "campusCode": "NB", "stopPoint": 10, "sectionEligibility": "JUNIORS AND SENIORS ", "sessionDatePrintIndicator": "Y", "openStatus": true}, {"minors": [], "sessionDates": null, "honorPrograms": [], "number": "07", "unitMajors": [], "subtitle": "ORAL HISTORY OF WWII                    ", "specialPermissionDropCodeDescription": null, "specialPermissionAddCodeDescription": "Instructor", "subtopic": null, "majors": [{"code": "510", "isUnitCode": false, "isMajorCode": true}, {"code": "514", "isUnitCode": false, "isMajorCode": true}], "index": "28016", "sectionNotes": null, "specialPermissionDropCode": null, "comments": [], "crossListedSections": [], "legendKey": null, "meetingTimes": [{"campusName": "COLLEGE AVENUE", "startTime": "0110", "meetingDay": "W", "meetingModeDesc": "SEM", "roomNumber": "105", "campusLocation": "1", "buildingCode": "SC", "pmCode": "P", "baClassHours": null, "campusAbbrev": "CAC", "endTime": "0410", "meetingModeCode": "04"}], "specialPermissionAddCode": "04", "instructors": [{"name": "CHAMBERS"}], "printed": "Y", "examCode": "C", "campusCode": "NB", "stopPoint": 15, "sectionEligibility": "JUNIORS AND SENIORS ", "sessionDatePrintIndicator": "Y", "openStatus": true}, {"minors": [], "sessionDates": null, "honorPrograms": [], "number": "09", "unitMajors": [], "subtitle": "PARENTS AND CHILDREN IN AMERICAN HISTORY", "specialPermissionDropCodeDescription": null, "specialPermissionAddCodeDescription": null, "subtopic": null, "majors": [{"code": "514", "isUnitCode": false, "isMajorCode": true}, {"code": "510", "isUnitCode": false, "isMajorCode": true}], "index": "31877", "sectionNotes": null, "specialPermissionDropCode": null, "comments": [], "crossListedSections": [], "legendKey": null, "meetingTimes": [{"campusName": "COLLEGE AVENUE", "startTime": "0250", "meetingDay": "W", "meetingModeDesc": "SEM", "roomNumber": "106", "campusLocation": "1", "buildingCode": "SC", "pmCode": "P", "baClassHours": null, "campusAbbrev": "CAC", "endTime": "0550", "meetingModeCode": "04"}], "specialPermissionAddCode": null, "instructors": [{"name": "FASS"}], "printed": "Y", "examCode": "C", "campusCode": "NB", "stopPoint": 15, "sectionEligibility": "JUNIORS AND SENIORS ", "sessionDatePrintIndicator": "Y", "openStatus": true}, {"minors": [], "sessionDates": null, "honorPrograms": [], "number": "10", "unitMajors": [], "subtitle": "WARS, REVOLUTION, AND HISTORICAL MEMORY ", "specialPermissionDropCodeDescription": null, "specialPermissionAddCodeDescription": null, "subtopic": null, "majors": [{"code": "514", "isUnitCode": false, "isMajorCode": true}, {"code": "510", "isUnitCode": false, "isMajorCode": true}], "index": "32989", "sectionNotes": null, "specialPermissionDropCode": null, "comments": [], "crossListedSections": [], "legendKey": null, "meetingTimes": [{"campusName": "COLLEGE AVENUE", "startTime": "0250", "meetingDay": "W", "meetingModeDesc": "SEM", "roomNumber": "204", "campusLocation": "1", "buildingCode": "SC", "pmCode": "P", "baClassHours": null, "campusAbbrev": "CAC", "endTime": "0550", "meetingModeCode": "04"}], "specialPermissionAddCode": null, "instructors": [{"name": "KAPLAN"}], "printed": "Y", "examCode": "C", "campusCode": "NB", "stopPoint": 15, "sectionEligibility": "JUNIORS AND SENIORS ", "sessionDatePrintIndicator": "Y", "openStatus": true}, {"minors": [], "sessionDates": null, "honorPrograms": [], "number": "14", "unitMajors": [], "subtitle": "GENDER AND CULTURE IN MODERN JAPAN      ", "specialPermissionDropCodeDescription": null, "specialPermissionAddCodeDescription": null, "subtopic": null, "majors": [{"code": "510", "isUnitCode": false, "isMajorCode": true}, {"code": "514", "isUnitCode": false, "isMajorCode": true}], "index": "26772", "sectionNotes": null, "specialPermissionDropCode": null, "comments": [], "crossListedSections": [], "legendKey": null, "meetingTimes": [{"campusName": "COLLEGE AVENUE", "startTime": "0110", "meetingDay": "F", "meetingModeDesc": "SEM", "roomNumber": "215", "campusLocation": "1", "buildingCode": "SC", "pmCode": "P", "baClassHours": null, "campusAbbrev": "CAC", "endTime": "0410", "meetingModeCode": "04"}], "specialPermissionAddCode": null, "instructors": [{"name": "RODEN, D"}], "printed": "Y", "examCode": "C", "campusCode": "NB", "stopPoint": 15, "sectionEligibility": "JUNIORS AND SENIORS ", "sessionDatePrintIndicator": "Y", "openStatus": true}], "subject": "506"}, {"unitNotes": null, "courseDescription": null, "subjectNotes": null, "coreCodes": [], "courseNotes": null, "title": "PUB HIST INTERNSHIP", "supplementCode": "  ", "subjectGroupNotes": null, "courseNumber": "451", "campusCode": "NB", "synopsisUrl": "http://history.rutgers.edu/undergraduate/undergraduate-courses/fall-2013-classes", "preReqNotes": null, "openSections": 1, "credits": 3, "offeringUnitCode": "01", "expandedTitle": null, "offeringUnitTitle": null, "sections": [{"minors": [], "sessionDates": null, "honorPrograms": [], "number": "01", "unitMajors": [], "subtitle": null, "specialPermissionDropCodeDescription": null, "specialPermissionAddCodeDescription": "Instructor", "subtopic": null, "majors": [{"code": "510", "isUnitCode": false, "isMajorCode": true}, {"code": "514", "isUnitCode": false, "isMajorCode": true}], "index": "22987", "sectionNotes": null, "specialPermissionDropCode": null, "comments": [], "crossListedSections": [], "legendKey": null, "meetingTimes": [{"campusName": null, "startTime": null, "meetingDay": null, "meetingModeDesc": "INTERNSP", "roomNumber": null, "campusLocation": null, "buildingCode": null, "pmCode": null, "baClassHours": "B", "campusAbbrev": null, "endTime": null, "meetingModeCode": "15"}], "specialPermissionAddCode": "04", "instructors": [{"name": "SARETZKY, G."}], "printed": "Y", "examCode": "A", "campusCode": "NB", "stopPoint": 20, "sectionEligibility": "JUNIORS AND SENIORS ", "sessionDatePrintIndicator": "Y", "openStatus": true}], "subject": "506"}, {"unitNotes": null, "courseDescription": null, "subjectNotes": null, "coreCodes": [], "courseNotes": null, "title": "GEN HIST INTERNSHIP", "supplementCode": "  ", "subjectGroupNotes": null, "courseNumber": "452", "campusCode": "NB", "synopsisUrl": "http://history.rutgers.edu/undergraduate/undergraduate-courses/fall-2013-classes", "preReqNotes": null, "openSections": 1, "credits": 3, "offeringUnitCode": "01", "expandedTitle": null, "offeringUnitTitle": null, "sections": [{"minors": [], "sessionDates": null, "honorPrograms": [], "number": "01", "unitMajors": [], "subtitle": null, "specialPermissionDropCodeDescription": null, "specialPermissionAddCodeDescription": "Instructor", "subtopic": null, "majors": [{"code": "510", "isUnitCode": false, "isMajorCode": true}, {"code": "514", "isUnitCode": false, "isMajorCode": true}], "index": "25000", "sectionNotes": null, "specialPermissionDropCode": null, "comments": [], "crossListedSections": [], "legendKey": null, "meetingTimes": [{"campusName": null, "startTime": null, "meetingDay": null, "meetingModeDesc": "INTERNSP", "roomNumber": null, "campusLocation": null, "buildingCode": null, "pmCode": null, "baClassHours": "B", "campusAbbrev": null, "endTime": null, "meetingModeCode": "15"}], "specialPermissionAddCode": "04", "instructors": [{"name": "SARETZKY, G."}], "printed": "Y", "examCode": "A", "campusCode": "NB", "stopPoint": 20, "sectionEligibility": "JUNIORS AND SENIORS ", "sessionDatePrintIndicator": "Y", "openStatus": true}], "subject": "506"}, {"unitNotes": null, "courseDescription": null, "subjectNotes": null, "coreCodes": [], "courseNotes": null, "title": "RESEARCH IN HISTORY", "supplementCode": "  ", "subjectGroupNotes": null, "courseNumber": "471", "campusCode": "NB", "synopsisUrl": "http://history.rutgers.edu/undergraduate/undergraduate-courses/fall-2013-classes", "preReqNotes": null, "openSections": 1, "credits": 3, "offeringUnitCode": "01", "expandedTitle": null, "offeringUnitTitle": null, "sections": [{"minors": [], "sessionDates": null, "honorPrograms": [], "number": "01", "unitMajors": [], "subtitle": null, "specialPermissionDropCodeDescription": null, "specialPermissionAddCodeDescription": "Department staff", "subtopic": null, "majors": [], "index": "20281", "sectionNotes": null, "specialPermissionDropCode": null, "comments": [], "crossListedSections": [], "legendKey": null, "meetingTimes": [{"campusName": null, "startTime": null, "meetingDay": null, "meetingModeDesc": "PROJ-IND", "roomNumber": null, "campusLocation": null, "buildingCode": null, "pmCode": null, "baClassHours": "B", "campusAbbrev": null, "endTime": null, "meetingModeCode": "19"}], "specialPermissionAddCode": "03", "instructors": [], "printed": "Y", "examCode": "O", "campusCode": "NB", "stopPoint": 50, "sectionEligibility": null, "sessionDatePrintIndicator": "Y", "openStatus": true}], "subject": "506"}, {"unitNotes": null, "courseDescription": null, "subjectNotes": null, "coreCodes": [], "courseNotes": null, "title": "READINGS IN HISTORY", "supplementCode": "  ", "subjectGroupNotes": null, "courseNumber": "473", "campusCode": "NB", "synopsisUrl": "http://history.rutgers.edu/undergraduate/undergraduate-courses/fall-2013-classes", "preReqNotes": null, "openSections": 1, "credits": 3, "offeringUnitCode": "01", "expandedTitle": null, "offeringUnitTitle": null, "sections": [{"minors": [], "sessionDates": null, "honorPrograms": [], "number": "01", "unitMajors": [], "subtitle": null, "specialPermissionDropCodeDescription": null, "specialPermissionAddCodeDescription": "Department staff", "subtopic": null, "majors": [], "index": "23141", "sectionNotes": null, "specialPermissionDropCode": null, "comments": [], "crossListedSections": [], "legendKey": null, "meetingTimes": [{"campusName": null, "startTime": null, "meetingDay": null, "meetingModeDesc": "READINGS", "roomNumber": null, "campusLocation": null, "buildingCode": null, "pmCode": null, "baClassHours": "B", "campusAbbrev": null, "endTime": null, "meetingModeCode": "18"}], "specialPermissionAddCode": "03", "instructors": [], "printed": "Y", "examCode": "A", "campusCode": "NB", "stopPoint": 40, "sectionEligibility": null, "sessionDatePrintIndicator": "Y", "openStatus": true}], "subject": "506"}, {"unitNotes": null, "courseDescription": null, "subjectNotes": null, "coreCodes": [{"code": "WCd", "description": "[Writing and Communication in a Discipline]", "effective": "20121", "course": "495", "supplement": null, "unit": "01", "subject": "506"}, {"code": "WCr", "description": "[Writing and Communication, Revision]", "effective": "20121", "course": "495", "supplement": null, "unit": "01", "subject": "506"}], "courseNotes": null, "title": "HONORS PROG IN HIST", "supplementCode": "  ", "subjectGroupNotes": null, "courseNumber": "495", "campusCode": "NB", "synopsisUrl": "http://history.rutgers.edu/undergraduate/undergraduate-courses/fall-2013-classes", "preReqNotes": null, "openSections": 2, "credits": null, "offeringUnitCode": "01", "expandedTitle": null, "offeringUnitTitle": null, "sections": [{"minors": [], "sessionDates": null, "honorPrograms": [], "number": "01", "unitMajors": [], "subtitle": null, "specialPermissionDropCodeDescription": null, "specialPermissionAddCodeDescription": "Department staff", "subtopic": null, "majors": [{"code": "514", "isUnitCode": false, "isMajorCode": true}, {"code": "510", "isUnitCode": false, "isMajorCode": true}], "index": "23375", "sectionNotes": null, "specialPermissionDropCode": null, "comments": [], "crossListedSections": [], "legendKey": null, "meetingTimes": [{"campusName": "COLLEGE AVENUE", "startTime": "1130", "meetingDay": "F", "meetingModeDesc": "PROJ-IND", "roomNumber": "301", "campusLocation": "1", "buildingCode": "VD", "pmCode": "A", "baClassHours": null, "campusAbbrev": "CAC", "endTime": "1250", "meetingModeCode": "19"}], "specialPermissionAddCode": "03", "instructors": [{"name": "WASSERMAN"}], "printed": "Y", "examCode": "A", "campusCode": "NB", "stopPoint": 20, "sectionEligibility": "JUNIORS AND SENIORS ", "sessionDatePrintIndicator": "Y", "openStatus": true}, {"minors": [], "sessionDates": null, "honorPrograms": [], "number": "02", "unitMajors": [], "subtitle": null, "specialPermissionDropCodeDescription": null, "specialPermissionAddCodeDescription": "Department staff", "subtopic": null, "majors": [{"code": "514", "isUnitCode": false, "isMajorCode": true}, {"code": "510", "isUnitCode": false, "isMajorCode": true}], "index": "23250", "sectionNotes": null, "specialPermissionDropCode": null, "comments": [], "crossListedSections": [], "legendKey": null, "meetingTimes": [{"campusName": "COLLEGE AVENUE", "startTime": "0110", "meetingDay": "F", "meetingModeDesc": "PROJ-IND", "roomNumber": "301", "campusLocation": "1", "buildingCode": "VD", "pmCode": "P", "baClassHours": null, "campusAbbrev": "CAC", "endTime": "0230", "meetingModeCode": "19"}], "specialPermissionAddCode": "03", "instructors": [{"name": "WASSERMAN"}], "printed": "Y", "examCode": "A", "campusCode": "NB", "stopPoint": 20, "sectionEligibility": "JUNIORS AND SENIORS ", "sessionDatePrintIndicator": "Y", "openStatus": true}], "subject": "506"}]